eurostatapiclient/__init__.py
eurostatapiclient/client.py
eurostatapiclient/models/__init__.py
eurostatapiclient/models/dataset.py
eurostatapiclient/models/dimension.py
eurostatapiclient/utils/__init__.py
eurostatapiclient/utils/property_decorators.py
eurostatapiclient-0.3.0.dist-info/LICENSE
eurostatapiclient-0.3.0.dist-info/METADATA
eurostatapiclient-0.3.0.dist-info/WHEEL
eurostatapiclient-0.3.0.dist-info/top_level.txt
eurostatapiclient-0.3.0.dist-info/RECORD
