Metadata-Version: 2.1
Name: eurostatapiclient
Version: 0.3.0
Summary: A simple Eurostat Rest API client
Home-page: https://github.com/opus-42/eurostat-api-client
Author: Emmanuel Bavoux
Author-email: emmanuel.bavoux@gmail.com
Classifier: Programming Language :: Python :: 3
Classifier: Development Status :: 4 - Beta
Classifier: License :: OSI Approved :: Apache Software License
Classifier: Operating System :: OS Independent
License-File: LICENSE
Requires-Dist: pandas (>=0.23.4)
Requires-Dist: requests (>=2.21.0)
